{"cell_id": "37UDQ4527", "theater_id": "ua_donbas", "label": "Unknown-61376", "admin_l1": null, "admin_l2": null, "admin_l3": null, "local_seq": 61376, "context": {"cell_id": "37UDQ4527", "theater_id": "ua_donbas", "mean_slope_deg": null, "dominant_landcover": 10, "landcover_label": "trees", "has_river": false, "has_bridge": false, "builtup_pct": 0.0025, "building_count": null, "nearest_road_class": "tertiary", "admin_l1": "Luhansk Oblast", "admin_l2": "Kreminna", "admin_l3": "Bilohorivska", "label": null}, "events": [{"event_id": "ea438da0-c3de-ad1c-84dc-1bda8cf1a8f8", "theater_id": "ua_donbas", "event_type": "fire", "cell_id": "37UDQ4527", "resolved_precision_m": 375.0, "occurred_start": "2026-06-29T05:43:00+05:30", "occurred_end": "2026-06-29T06:43:00+05:30", "status": "candidate", "confidence": 0.85, "confidence_band": "Rumored", "n_sources": 1, "n_independent_families": 1, "flags": ["single-source", "verification-needed"], "created_from_obs": ["88c40163-f52b-639d-a5cd-58b9b26d73dc"], "updated_at": "2026-07-01T12:21:30.380524+05:30", "centroid": {"type": "Point", "coordinates": [38.254984, 48.997942]}, "geometry": {"type": "Polygon", "coordinates": [[[38.248139, 48.99345], [38.248139, 49.002433], [38.26183, 49.002433], [38.26183, 48.99345], [38.248139, 48.99345]]]}, "place": {"name": "Rubizhne", "label": "near Rubizhne", "distance_km": 9.4}, "geo_context": null}], "centroid": {"type": "Point", "coordinates": [38.254984, 48.997942]}, "geometry": {"type": "Polygon", "coordinates": [[[38.248139, 48.99345], [38.248139, 49.002433], [38.26183, 49.002433], [38.26183, 48.99345], [38.248139, 48.99345]]]}}