{"area": {"ref": "admin:10664576B30103346668617", "kind": "admin", "label": "Shchastynska", "theater": "ua_donbas", "level": 3}, "read": {"summary": "Shchastynska: 4 recorded events, mostly strike. Activity is steady (0 in the last 45 days vs 0 before).", "indicators": "steady", "provenance": ["damage assessment", "news/reports"], "generated_by": "template"}, "attention": {"status": "steady", "recent": 0, "prior": 0, "confirmed": 0, "trend_score": 0.0, "has_spike": false, "has_escalation": false}, "terrain": {"landcover": {"built-up": 0.8, "trees": 0.2}, "builtup_pct": 0.46182, "road_unpaved_share": 0.0, "n_cells": 5}, "recent": [], "significant": [], "children": []}