{"area": {"ref": "admin:10664576B77042865194654", "kind": "admin", "label": "Novodmytrivska", "theater": "ua_donbas", "level": 3}, "read": {"summary": "Novodmytrivska: 8 recorded events, mostly strike. Activity is steady (0 in the last 45 days vs 0 before).", "indicators": "steady", "provenance": ["news/reports"], "generated_by": "template"}, "attention": {"status": "steady", "recent": 0, "prior": 0, "confirmed": 0, "trend_score": 0.0, "has_spike": false, "has_escalation": false}, "terrain": {"landcover": {"cropland": 0.7291666666666666, "grassland": 0.25, "trees": 0.020833333333333332}, "builtup_pct": 0.00493125, "road_unpaved_share": 0.7142857142857143, "n_cells": 48}, "recent": [], "significant": [], "children": []}